sphinx_icontract
sphinx_icontract_meta
