Metadata-Version: 1.1
Name: sphinx-icontract
Version: 2.0.0
Summary: Extend sphinx to include icontracts.
Home-page: https://github.com/Parquery/sphinx-icontract
Author: Marko Ristin
Author-email: marko.ristin@gmail.com
License: License :: OSI Approved :: MIT License
Keywords: contracts sphinx extension icontract design-by-contract
Platform: UNKNOWN
Classifier: Development Status :: 5 - Production/Stable
Classifier: Intended Audience :: Developers
Classifier: License :: OSI Approved :: MIT License
Classifier: Programming Language :: Python :: 3.5
Classifier: Programming Language :: Python :: 3.6
